singer_runner/__init__.py
singer_runner/cli.py
singer_runner/process.py
singer_runner/runner.py
singer_runner/utils.py
singer_runner/metrics/__init__.py
singer_runner/metrics/base.py
singer_runner/metrics/file.py
singer_runner/pipes/__init__.py
singer_runner/pipes/base.py
singer_runner/pipes/file.py
singer_runner/pipes/gcs.py
singer_runner/pipes/memory.py
singer_runner/pipes/stdinout.py
singer_runner/state/__init__.py
singer_runner/state/base.py
singer_runner/state/file.py
singer_runner-0.0.2.dist-info/LICENSE
singer_runner-0.0.2.dist-info/METADATA
singer_runner-0.0.2.dist-info/WHEEL
singer_runner-0.0.2.dist-info/entry_points.txt
singer_runner-0.0.2.dist-info/top_level.txt
singer_runner-0.0.2.dist-info/RECORD
