Metadata-Version: 2.1
Name: singer-runner
Version: 0.0.2
Summary: Runs Singer.io taps and targets, adding additional tooling.
Home-page: https://github.com/datamill-co/singer-runner
Author: datamill
License: UNKNOWN
Platform: UNKNOWN
Classifier: Programming Language :: Python :: 3 :: Only
Requires-Dist: pyyaml (>=4.2b1)
Requires-Dist: smart-open (==1.8.0)
Requires-Dist: click (==7.0)
Provides-Extra: gcs
Requires-Dist: google-cloud-storage (==1.15.1) ; extra == 'gcs'
